openfisca_paris/__init__.py
openfisca_paris/paris.py
openfisca_paris/paris_complement_sante.py
openfisca_paris/paris_logement.py
openfisca_paris/paris_logement_fam.py
openfisca_paris/paris_logement_fam_mono.py
openfisca_paris/paris_pass.py
openfisca_paris/paris_solidarite.py
openfisca_paris/familles/aspeh.py
openfisca_paris/familles/paris_energie_familles.py
openfisca_paris/familles/paris_forfait_familles.py
openfisca_paris/parameters/paris/paris_pass.yaml
openfisca_paris/parameters/paris/smic_net_mensuel.yaml
openfisca_paris/parameters/paris/familles/paris_energie_familles.yaml
openfisca_paris/parameters/paris/familles/paris_forfait_familles.yaml
openfisca_paris/parameters/paris/familles/aspeh/aide_aspeh.yaml
openfisca_paris/parameters/paris/familles/aspeh/plafond_aspeh.yaml
openfisca_paris/parameters/paris/paris_logement/aide_couple_avec_enf.yaml
openfisca_paris/parameters/paris/paris_logement/aide_couple_ss_enf.yaml
openfisca_paris/parameters/paris/paris_logement/aide_pers_isol.yaml
openfisca_paris/parameters/paris/paris_logement/plafond_pl_couple_avec_enf.yaml
openfisca_paris/parameters/paris/paris_logement/plafond_pl_couple_sans_enf.yaml
openfisca_paris/parameters/paris/paris_logement/plafond_pl_personne_isolee.yaml
openfisca_paris/parameters/paris/paris_logement/taux_effort_min.yaml
openfisca_paris/parameters/paris/paris_logement_familles/montant_2enf.yaml
openfisca_paris/parameters/paris/paris_logement_familles/montant_bas_3enf.yaml
openfisca_paris/parameters/paris/paris_logement_familles/montant_bas_enf_sup.yaml
openfisca_paris/parameters/paris/paris_logement_familles/montant_haut_3enf.yaml
openfisca_paris/parameters/paris/paris_logement_familles/montant_haut_enf_sup.yaml
openfisca_paris/parameters/paris/paris_logement_familles/plafond_2enf.yaml
openfisca_paris/parameters/paris/paris_logement_familles/plafond_bas_3enf.yaml
openfisca_paris/parameters/paris/paris_logement_familles/plafond_haut_3enf.yaml
openfisca_paris-5.5.14.dist-info/licenses/LICENSE.AGPL.txt
openfisca_paris-5.5.14.dist-info/METADATA
openfisca_paris-5.5.14.dist-info/WHEEL
openfisca_paris-5.5.14.dist-info/top_level.txt
openfisca_paris-5.5.14.dist-info/RECORD
