Metadata-Version: 2.4
Name: Openfisca-Paris
Version: 5.5.14
Summary: Plugin OpenFisca pour les aides sociales de la mairie de Paris
Author: OpenFisca Team
Author-email: contact@openfisca.fr
License: http://www.fsf.org/licensing/licenses/agpl-3.0.html
Keywords: benefit france paris microsimulation social tax
Classifier: Development Status :: 5 - Production/Stable
Classifier: License :: OSI Approved :: GNU Affero General Public License v3
Classifier: Operating System :: POSIX
Classifier: Programming Language :: Python
Classifier: Programming Language :: Python :: 3.9
Classifier: Programming Language :: Python :: 3.10
Classifier: Programming Language :: Python :: 3.11
Classifier: Topic :: Scientific/Engineering :: Information Analysis
License-File: LICENSE.AGPL.txt
Requires-Dist: OpenFisca-Core<45,>=43
Requires-Dist: OpenFisca-France<176.0.0,>=169.0.0
Provides-Extra: test
Requires-Dist: nose; extra == "test"
Requires-Dist: pytest>=5.4.2; extra == "test"
Dynamic: author
Dynamic: author-email
Dynamic: classifier
Dynamic: description-content-type
Dynamic: keywords
Dynamic: license
Dynamic: license-file
Dynamic: provides-extra
Dynamic: requires-dist
Dynamic: summary
